{
  "pins": {
    "lix": {
      "type": "Git",
      "repository": {
        "type": "Git",
        "url": "https://git.lix.systems/lix-project/lix.git"
      },
      "branch": "main",
      "submodules": false,
      "revision": "91bf54d726cddd74d6ca34c6c01de2c9461cbe32",
      "url": null,
      "hash": "02c84cp6zv7hvy2r3wci5qziv9smb1xsbcmk552yfk9hslnmw6hh"
    },
    "lix-nixos-module": {
      "type": "Git",
      "repository": {
        "type": "Git",
        "url": "https://git.lix.systems/lix-project/nixos-module"
      },
      "branch": "main",
      "submodules": false,
      "revision": "3f09a5eb772e02d98bb8878ab687d5b721f00d16",
      "url": null,
      "hash": "1jv8whspf1r5fkjv7l7phh0sjdbimfwh3n5gjhq22wgc3qjza012"
    },
    "nixos-hardware": {
      "type": "Git",
      "repository": {
        "type": "GitHub",
        "owner": "NixOS",
        "repo": "nixos-hardware"
      },
      "branch": "master",
      "submodules": false,
      "revision": "11b2a10c7be726321bb854403fdeec391e798bf0",
      "url": "https://github.com/NixOS/nixos-hardware/archive/11b2a10c7be726321bb854403fdeec391e798bf0.tar.gz",
      "hash": "0saswrdg59v4xfwfl7q61b47davz6yf58xfj707wzcip3s5zpm1y"
    },
    "nixpkgs": {
      "type": "Channel",
      "name": "nixos-unstable",
      "url": "https://releases.nixos.org/nixos/unstable/nixos-25.11pre858212.b599843bad24/nixexprs.tar.xz",
      "hash": "1hljkbhlv98h32sdzgjw7c5nqjyfrxfnqh0ffwyy4xljfrkjak3i"
    }
  },
  "version": 5
}
